nonebot_plugin_withdraw/__init__.py
nonebot_plugin_withdraw/adapters/__init__.py
nonebot_plugin_withdraw/adapters/discord.py
nonebot_plugin_withdraw/adapters/dodo.py
nonebot_plugin_withdraw/adapters/feishu.py
nonebot_plugin_withdraw/adapters/kaiheila.py
nonebot_plugin_withdraw/adapters/onebot_v11.py
nonebot_plugin_withdraw/adapters/onebot_v12.py
nonebot_plugin_withdraw/adapters/qq.py
nonebot_plugin_withdraw/adapters/red.py
nonebot_plugin_withdraw/adapters/satori.py
nonebot_plugin_withdraw/adapters/telegram.py
nonebot_plugin_withdraw/config.py
nonebot_plugin_withdraw/handler.py
nonebot_plugin_withdraw/receipt.py
nonebot_plugin_withdraw-0.4.0.dist-info/LICENSE
nonebot_plugin_withdraw-0.4.0.dist-info/METADATA
nonebot_plugin_withdraw-0.4.0.dist-info/WHEEL
nonebot_plugin_withdraw-0.4.0.dist-info/RECORD
